{
  "奄美大島北東沖": {
    "lat": 28.3,
    "lon": 131.3
  },
  "福島県沖": {
    "lat": 37.3,
    "lon": 141.8
  },
  "千葉県北西部": {
    "lat": 35.8,
    "lon": 140.2
  },
  "新潟県上中越沖": {
    "lat": 37.6,
    "lon": 138.1
  },
  "鹿児島県薩摩地方": {
    "lat": 32.1,
    "lon": 130.4
  },
  "岩手県沖": {
    "lat": 40.1,
    "lon": 142.4
  },
  "長野県中部": {
    "lat": 36.2,
    "lon": 137.6
  },
  "岐阜県飛騨地方": {
    "lat": 36.2,
    "lon": 137.5
  },
  "三陸沖": {
    "lat": 39.8,
    "lon": 143.4
  },
  "茨城県北部": {
    "lat": 36.6,
    "lon": 140.6
  },
  "長野県北部": {
    "lat": 36.5,
    "lon": 137.9
  },
  "紀伊水道": {
    "lat": 34.2,
    "lon": 135.1
  },
  "石川県加賀地方": {
    "lat": 36.3,
    "lon": 136.7
  },
  "青森県東方沖": {
    "lat": 40.5,
    "lon": 142.6
  },
  "和歌山県北部": {
    "lat": 34.1,
    "lon": 135.4
  },
  "熊本県阿蘇地方": {
    "lat": 33,
    "lon": 131.1
  },
  "島根県東部": {
    "lat": 35.3,
    "lon": 133.2
  },
  "石川県能登地方": {
    "lat": 37.2,
    "lon": 136.7
  },
  "宗谷地方南部": {
    "lat": 45.1,
    "lon": 142.2
  },
  "トカラ列島近海": {
    "lat": 29.3,
    "lon": 129.6
  },
  "豊後水道": {
    "lat": 33.4,
    "lon": 132.3
  },
  "熊本県熊本地方": {
    "lat": 32.8,
    "lon": 130.7
  },
  "千葉県南部": {
    "lat": 35.1,
    "lon": 140
  },
  "熊本県球磨地方": {
    "lat": 32.4,
    "lon": 130.8
  },
  "富山湾": {
    "lat": 37.2,
    "lon": 137.5
  },
  "千島列島": {
    "lat": 45.8,
    "lon": 151.9
  },
  "沖縄本島近海": {
    "lat": 26.7,
    "lon": 127.7
  },
  "富山県東部": {
    "lat": 36.4,
    "lon": 137.6
  },
  "青森県三八上北地方": {
    "lat": 40.4,
    "lon": 141.2
  },
  "茨城県沖": {
    "lat": 36.5,
    "lon": 141
  },
  "北海道東方沖": {
    "lat": 43.4,
    "lon": 146.6
  },
  "山梨県東部・富士五湖": {
    "lat": 35.5,
    "lon": 139
  },
  "熊本県天草・芦北地方": {
    "lat": 32.3,
    "lon": 130.4
  },
  "宮城県沖": {
    "lat": 38.2,
    "lon": 141.8
  },
  "釧路沖": {
    "lat": 41.8,
    "lon": 146.4
  },
  "岩手県沿岸北部": {
    "lat": 39.8,
    "lon": 141.8
  },
  "大阪府北部": {
    "lat": 34.8,
    "lon": 135.6
  },
  "宮古島近海": {
    "lat": 25.3,
    "lon": 125.2
  },
  "徳島県北部": {
    "lat": 34,
    "lon": 134.2
  },
  "東京都多摩西部": {
    "lat": 35.8,
    "lon": 139.3
  },
  "伊予灘": {
    "lat": 33.7,
    "lon": 132.3
  },
  "淡路島付近": {
    "lat": 34.3,
    "lon": 134.8
  },
  "十勝沖": {
    "lat": 41.8,
    "lon": 144.3
  },
  "上川地方南部": {
    "lat": 43,
    "lon": 142.3
  },
  "茨城県南部": {
    "lat": 36,
    "lon": 140.2
  },
  "南海道南方沖": {
    "lat": 32,
    "lon": 135.9
  },
  "高知県中部": {
    "lat": 33.8,
    "lon": 134
  },
  "神奈川県西部": {
    "lat": 35.6,
    "lon": 139.2
  },
  "父島近海": {
    "lat": 27.9,
    "lon": 142.9
  },
  "兵庫県南東部": {
    "lat": 34.7,
    "lon": 135.2
  }
}